<?xml version="1.0" encoding="utf-8"?>

<odoo>
	<data>

		<!--
				Sale: (sale_operating_unit)
		-->
		<record id="view_order_form_inherit2" model="ir.ui.view">
			<field name="name">sale.view_order_form.inherit2</field>
			<field name="model">sale.order</field>
			<field name="inherit_id" ref="sale_operating_unit.view_order_form"/>
			<field name="type">form</field>
			<field name="arch" type="xml">
				<xpath expr="//field[@name='operating_unit_id']" position="attributes">
                    <attribute name="on_change">0</attribute>
                </xpath>
            </field>
        </record>

    </data>
</odoo>